[{
	"id": 1,
	"Name": "Douglas Riley",
	"Email": "driley0@businessinsider.com",
	"Phone": "1-(312)918-5532",
	"Address": "3585 South Road",
	"City": "Chicago",
	"Zipcode": "60691",
	"State": "Illinois"
}, {
	"id": 2,
	"Name": "Frances Ford",
	"Email": "fford1@pbs.org",
	"Phone": "1-(916)196-6444",
	"Address": "94405 Ronald Regan Street",
	"City": "Sacramento",
	"Zipcode": "94286",
	"State": "California"
}, {
	"id": 3,
	"Name": "Gerald Spencer",
	"Email": "gspencer2@fda.gov",
	"Phone": "1-(541)189-5079",
	"Address": "1 Green Crossing",
	"City": "Eugene",
	"Zipcode": "97405",
	"State": "Oregon"
}, {
	"id": 4,
	"Name": "Gary Riley",
	"Email": "griley3@cisco.com",
	"Phone": "1-(352)969-3077",
	"Address": "2389 Fuller Drive",
	"City": "Brooksville",
	"Zipcode": "34605",
	"State": "Florida"
}, {
	"id": 5,
	"Name": "Roy Simmons",
	"Email": "rsimmons4@uiuc.edu",
	"Phone": "1-(316)994-3088",
	"Address": "3 Nevada Hill",
	"City": "Wichita",
	"Zipcode": "67236",
	"State": "Kansas"
}, {
	"id": 6,
	"Name": "Nancy Hamilton",
	"Email": "nhamilton5@vinaora.com",
	"Phone": "1-(760)457-2822",
	"Address": "07713 Sauthoff Court",
	"City": "San Diego",
	"Zipcode": "92121",
	"State": "California"
}, {
	"id": 7,
	"Name": "Virginia Hunt",
	"Email": "vhunt6@theatlantic.com",
	"Phone": "1-(518)838-6364",
	"Address": "9 Sage Point",
	"City": "Albany",
	"Zipcode": "12247",
	"State": "New York"
}, {
	"id": 8,
	"Name": "Cheryl Carter",
	"Email": "ccarter7@sphinn.com",
	"Phone": "1-(682)742-7364",
	"Address": "40 South Road",
	"City": "Fort Worth",
	"Zipcode": "76178",
	"State": "Texas"
}, {
	"id": 9,
	"Name": "Timothy Simpson",
	"Email": "tsimpson8@examiner.com",
	"Phone": "1-(214)503-5884",
	"Address": "58 Del Mar Lane",
	"City": "Dallas",
	"Zipcode": "75342",
	"State": "Texas"
}, {
	"id": 10,
	"Name": "Edward Adams",
	"Email": "eadams9@businessweek.com",
	"Phone": "1-(212)918-3350",
	"Address": "6 Shoshone Pass",
	"City": "Brooklyn",
	"Zipcode": "11247",
	"State": "New York"
}, {
	"id": 11,
	"Name": "Wanda Myers",
	"Email": "wmyersa@sina.com.cn",
	"Phone": "1-(412)708-4378",
	"Address": "44 Scofield Center",
	"City": "Mc Keesport",
	"Zipcode": "15134",
	"State": "Pennsylvania"
}, {
	"id": 12,
	"Name": "Larry Cook",
	"Email": "lcookb@state.gov",
	"Phone": "1-(540)382-4021",
	"Address": "93995 Texas Pass",
	"City": "Roanoke",
	"Zipcode": "24029",
	"State": "Virginia"
}, {
	"id": 13,
	"Name": "Howard Perkins",
	"Email": "hperkinsc@mysql.com",
	"Phone": "1-(323)812-8581",
	"Address": "3554 Spohn Plaza",
	"City": "Los Angeles",
	"Zipcode": "90071",
	"State": "California"
}, {
	"id": 14,
	"Name": "Jeffrey Hayes",
	"Email": "jhayesd@apple.com",
	"Phone": "1-(202)497-8754",
	"Address": "4591 Anzinger Way",
	"City": "Washington",
	"Zipcode": "20073",
	"State": "District of Columbia"
}, {
	"id": 15,
	"Name": "Aaron Carr",
	"Email": "acarre@studiopress.com",
	"Phone": "1-(816)619-9072",
	"Address": "8 Clarendon Plaza",
	"City": "Kansas City",
	"Zipcode": "64149",
	"State": "Missouri"
}, {
	"id": 16,
	"Name": "George Alexander",
	"Email": "galexanderf@cbslocal.com",
	"Phone": "1-(803)810-6114",
	"Address": "018 Victoria Place",
	"City": "Columbia",
	"Zipcode": "29220",
	"State": "South Carolina"
}, {
	"id": 17,
	"Name": "Raymond Mcdonald",
	"Email": "rmcdonaldg@china.com.cn",
	"Phone": "1-(614)163-9030",
	"Address": "97 Sommers Place",
	"City": "Columbus",
	"Zipcode": "43240",
	"State": "Ohio"
}, {
	"id": 18,
	"Name": "Donald Young",
	"Email": "dyoungh@themeforest.net",
	"Phone": "1-(501)687-3835",
	"Address": "1756 Randy Point",
	"City": "North Little Rock",
	"Zipcode": "72118",
	"State": "Arkansas"
}, {
	"id": 19,
	"Name": "Joan Tucker",
	"Email": "jtuckeri@vkontakte.ru",
	"Phone": "1-(814)128-9239",
	"Address": "6033 Portage Circle",
	"City": "Erie",
	"Zipcode": "16534",
	"State": "Pennsylvania"
}, {
	"id": 20,
	"Name": "Clarence Fernandez",
	"Email": "cfernandezj@samsung.com",
	"Phone": "1-(785)451-5623",
	"Address": "582 Karstens Pass",
	"City": "Topeka",
	"Zipcode": "66642",
	"State": "Kansas"
}, {
	"id": 21,
	"Name": "Anne Sims",
	"Email": "asimsk@icio.us",
	"Phone": "1-(847)710-5127",
	"Address": "0025 Carioca Street",
	"City": "Palatine",
	"Zipcode": "60078",
	"State": "Illinois"
}, {
	"id": 22,
	"Name": "Paula Simpson",
	"Email": "psimpsonl@bandcamp.com",
	"Phone": "1-(361)939-2585",
	"Address": "6133 North Drive",
	"City": "Corpus Christi",
	"Zipcode": "78410",
	"State": "Texas"
}, {
	"id": 23,
	"Name": "Diana Frazier",
	"Email": "dfrazierm@google.it",
	"Phone": "1-(713)521-0987",
	"Address": "3743 Bobwhite Circle",
	"City": "Houston",
	"Zipcode": "77271",
	"State": "Texas"
}, {
	"id": 24,
	"Name": "Jennifer Jones",
	"Email": "jjonesn@histats.com",
	"Phone": "1-(281)662-6747",
	"Address": "9 Forster Point",
	"City": "Galveston",
	"Zipcode": "77554",
	"State": "Texas"
}, {
	"id": 25,
	"Name": "Peter Spencer",
	"Email": "pspencero@adobe.com",
	"Phone": "1-(718)902-5322",
	"Address": "1937 Hudson Circle",
	"City": "Bronx",
	"Zipcode": "10474",
	"State": "New York"
}, {
	"id": 26,
	"Name": "Kevin Kennedy",
	"Email": "kkennedyp@princeton.edu",
	"Phone": "1-(216)427-2654",
	"Address": "85 Brentwood Crossing",
	"City": "Cleveland",
	"Zipcode": "44118",
	"State": "Ohio"
}, {
	"id": 27,
	"Name": "Joan Brooks",
	"Email": "jbrooksq@meetup.com",
	"Phone": "1-(702)118-2648",
	"Address": "1 Eagan Avenue",
	"City": "Las Vegas",
	"Zipcode": "89193",
	"State": "Nevada"
}, {
	"id": 28,
	"Name": "Nicholas Fox",
	"Email": "nfoxr@yahoo.co.jp",
	"Phone": "1-(847)114-1048",
	"Address": "41 Village Road",
	"City": "Evanston",
	"Zipcode": "60208",
	"State": "Illinois"
}, {
	"id": 29,
	"Name": "Louis Davis",
	"Email": "ldaviss@uiuc.edu",
	"Phone": "1-(704)855-7018",
	"Address": "92 Walton Street",
	"City": "Charlotte",
	"Zipcode": "28220",
	"State": "North Carolina"
}, {
	"id": 30,
	"Name": "Patrick Carter",
	"Email": "pcartert@bizjournals.com",
	"Phone": "1-(253)132-2603",
	"Address": "01 Aberg Plaza",
	"City": "Seattle",
	"Zipcode": "98148",
	"State": "Washington"
}, {
	"id": 31,
	"Name": "Steven Brown",
	"Email": "sbrownu@prweb.com",
	"Phone": "1-(360)921-7665",
	"Address": "4061 Pepper Wood Terrace",
	"City": "Olympia",
	"Zipcode": "98516",
	"State": "Washington"
}, {
	"id": 32,
	"Name": "Benjamin Gray",
	"Email": "bgrayv@usda.gov",
	"Phone": "1-(713)904-0697",
	"Address": "9 Sunfield Center",
	"City": "Houston",
	"Zipcode": "77020",
	"State": "Texas"
}, {
	"id": 33,
	"Name": "Russell Mills",
	"Email": "rmillsw@globo.com",
	"Phone": "1-(954)731-2982",
	"Address": "8 Pearson Court",
	"City": "West Palm Beach",
	"Zipcode": "33411",
	"State": "Florida"
}, {
	"id": 34,
	"Name": "Carol Hughes",
	"Email": "chughesx@altervista.org",
	"Phone": "1-(301)561-2050",
	"Address": "03398 Independence Junction",
	"City": "Bethesda",
	"Zipcode": "20816",
	"State": "Maryland"
}, {
	"id": 35,
	"Name": "Cheryl Fowler",
	"Email": "cfowlery@virginia.edu",
	"Phone": "1-(408)898-6625",
	"Address": "108 Holmberg Point",
	"City": "San Jose",
	"Zipcode": "95123",
	"State": "California"
}, {
	"id": 36,
	"Name": "Deborah Marshall",
	"Email": "dmarshallz@usa.gov",
	"Phone": "1-(501)711-6049",
	"Address": "7165 Upham Crossing",
	"City": "Little Rock",
	"Zipcode": "72204",
	"State": "Arkansas"
}, {
	"id": 37,
	"Name": "Sara Weaver",
	"Email": "sweaver10@drupal.org",
	"Phone": "1-(707)431-5172",
	"Address": "45 Banding Terrace",
	"City": "Santa Rosa",
	"Zipcode": "95405",
	"State": "California"
}, {
	"id": 38,
	"Name": "Barbara Greene",
	"Email": "bgreene11@phpbb.com",
	"Phone": "1-(954)221-5104",
	"Address": "358 Sullivan Avenue",
	"City": "Pompano Beach",
	"Zipcode": "33064",
	"State": "Florida"
}, {
	"id": 39,
	"Name": "Elizabeth Morgan",
	"Email": "emorgan12@gov.uk",
	"Phone": "1-(212)334-8766",
	"Address": "3 Everett Avenue",
	"City": "New York City",
	"Zipcode": "10004",
	"State": "New York"
}, {
	"id": 40,
	"Name": "Ruby Peterson",
	"Email": "rpeterson13@pagesperso-orange.fr",
	"Phone": "1-(610)387-7041",
	"Address": "0 Lindbergh Hill",
	"City": "Philadelphia",
	"Zipcode": "19109",
	"State": "Pennsylvania"
}, {
	"id": 41,
	"Name": "Jonathan Wright",
	"Email": "jwright14@w3.org",
	"Phone": "1-(303)322-6830",
	"Address": "8 Knutson Place",
	"City": "Aurora",
	"Zipcode": "80044",
	"State": "Colorado"
}, {
	"id": 42,
	"Name": "Jesse Reid",
	"Email": "jreid15@blogs.com",
	"Phone": "1-(206)954-1268",
	"Address": "18 Nancy Park",
	"City": "Seattle",
	"Zipcode": "98195",
	"State": "Washington"
}, {
	"id": 43,
	"Name": "Ann Bishop",
	"Email": "abishop16@twitter.com",
	"Phone": "1-(251)961-9300",
	"Address": "85 Becker Trail",
	"City": "Mobile",
	"Zipcode": "36622",
	"State": "Alabama"
}, {
	"id": 44,
	"Name": "Anthony Riley",
	"Email": "ariley17@oakley.com",
	"Phone": "1-(712)625-5191",
	"Address": "2 Charing Cross Plaza",
	"City": "Sioux City",
	"Zipcode": "51105",
	"State": "Iowa"
}, {
	"id": 45,
	"Name": "Charles Perkins",
	"Email": "cperkins18@geocities.jp",
	"Phone": "1-(717)208-5142",
	"Address": "20 Marquette Hill",
	"City": "Harrisburg",
	"Zipcode": "17105",
	"State": "Pennsylvania"
}, {
	"id": 46,
	"Name": "Wanda Allen",
	"Email": "wallen19@wufoo.com",
	"Phone": "1-(414)367-8455",
	"Address": "71826 Toban Alley",
	"City": "Milwaukee",
	"Zipcode": "53277",
	"State": "Wisconsin"
}, {
	"id": 47,
	"Name": "Diane Matthews",
	"Email": "dmatthews1a@addthis.com",
	"Phone": "1-(954)655-4131",
	"Address": "8132 Comanche Hill",
	"City": "Fort Lauderdale",
	"Zipcode": "33330",
	"State": "Florida"
}, {
	"id": 48,
	"Name": "Mark Ramirez",
	"Email": "mramirez1b@pcworld.com",
	"Phone": "1-(772)540-4272",
	"Address": "40 Rutledge Street",
	"City": "Fort Pierce",
	"Zipcode": "34981",
	"State": "Florida"
}, {
	"id": 49,
	"Name": "Antonio Green",
	"Email": "agreen1c@yahoo.com",
	"Phone": "1-(814)915-4151",
	"Address": "1 Eliot Junction",
	"City": "Erie",
	"Zipcode": "16505",
	"State": "Pennsylvania"
}, {
	"id": 50,
	"Name": "Stephen Franklin",
	"Email": "sfranklin1d@sun.com",
	"Phone": "1-(904)572-4997",
	"Address": "36262 Melvin Park",
	"City": "Jacksonville",
	"Zipcode": "32244",
	"State": "Florida"
}, {
	"id": 51,
	"Name": "Jonathan Lawrence",
	"Email": "jlawrence1e@usatoday.com",
	"Phone": "1-(757)252-3481",
	"Address": "345 Atwood Circle",
	"City": "Virginia Beach",
	"Zipcode": "23454",
	"State": "Virginia"
}, {
	"id": 52,
	"Name": "Patricia Morris",
	"Email": "pmorris1f@reuters.com",
	"Phone": "1-(419)883-9103",
	"Address": "102 Bartelt Circle",
	"City": "Toledo",
	"Zipcode": "43699",
	"State": "Ohio"
}, {
	"id": 53,
	"Name": "Ronald Banks",
	"Email": "rbanks1g@51.la",
	"Phone": "1-(714)413-0240",
	"Address": "36832 Buell Way",
	"City": "Fullerton",
	"Zipcode": "92835",
	"State": "California"
}, {
	"id": 54,
	"Name": "Stephen Jackson",
	"Email": "sjackson1h@liveinternet.ru",
	"Phone": "1-(520)166-9788",
	"Address": "51292 Onsgard Road",
	"City": "Tucson",
	"Zipcode": "85710",
	"State": "Arizona"
}, {
	"id": 55,
	"Name": "Betty Allen",
	"Email": "ballen1i@163.com",
	"Phone": "1-(501)491-0914",
	"Address": "92 Butternut Circle",
	"City": "Little Rock",
	"Zipcode": "72231",
	"State": "Arkansas"
}, {
	"id": 56,
	"Name": "Brandon Clark",
	"Email": "bclark1j@t.co",
	"Phone": "1-(313)350-6894",
	"Address": "81802 Old Shore Place",
	"City": "Detroit",
	"Zipcode": "48232",
	"State": "Michigan"
}, {
	"id": 57,
	"Name": "Carolyn Martinez",
	"Email": "cmartinez1k@tumblr.com",
	"Phone": "1-(913)856-8884",
	"Address": "18 Hayes Court",
	"City": "Kansas City",
	"Zipcode": "66160",
	"State": "Kansas"
}, {
	"id": 58,
	"Name": "Paul Fowler",
	"Email": "pfowler1l@businessinsider.com",
	"Phone": "1-(253)924-9797",
	"Address": "5 Thackeray Place",
	"City": "Tacoma",
	"Zipcode": "98464",
	"State": "Washington"
}, {
	"id": 59,
	"Name": "Beverly Hamilton",
	"Email": "bhamilton1m@ca.gov",
	"Phone": "1-(269)196-7248",
	"Address": "45 Randy Junction",
	"City": "Kalamazoo",
	"Zipcode": "49006",
	"State": "Michigan"
}, {
	"id": 60,
	"Name": "Marilyn Perkins",
	"Email": "mperkins1n@alibaba.com",
	"Phone": "1-(713)226-6080",
	"Address": "7801 Killdeer Drive",
	"City": "Houston",
	"Zipcode": "77250",
	"State": "Texas"
}, {
	"id": 61,
	"Name": "Janice Knight",
	"Email": "jknight1o@last.fm",
	"Phone": "1-(202)328-8266",
	"Address": "26388 Debra Court",
	"City": "Washington",
	"Zipcode": "20244",
	"State": "District of Columbia"
}, {
	"id": 62,
	"Name": "Joshua Reid",
	"Email": "jreid1p@trellian.com",
	"Phone": "1-(518)309-3348",
	"Address": "462 3rd Alley",
	"City": "Schenectady",
	"Zipcode": "12305",
	"State": "New York"
}, {
	"id": 63,
	"Name": "Wayne Nelson",
	"Email": "wnelson1q@altervista.org",
	"Phone": "1-(626)557-5254",
	"Address": "8 Katie Road",
	"City": "Pasadena",
	"Zipcode": "91125",
	"State": "California"
}, {
	"id": 64,
	"Name": "Rebecca Nelson",
	"Email": "rnelson1r@umich.edu",
	"Phone": "1-(585)739-6498",
	"Address": "0500 Doe Crossing Way",
	"City": "Rochester",
	"Zipcode": "14624",
	"State": "New York"
}, {
	"id": 65,
	"Name": "Theresa Fowler",
	"Email": "tfowler1s@about.com",
	"Phone": "1-(216)882-3384",
	"Address": "66 Sachs Court",
	"City": "Cleveland",
	"Zipcode": "44177",
	"State": "Ohio"
}, {
	"id": 66,
	"Name": "Julie Foster",
	"Email": "jfoster1t@naver.com",
	"Phone": "1-(317)603-9022",
	"Address": "7778 Declaration Pass",
	"City": "Indianapolis",
	"Zipcode": "46239",
	"State": "Indiana"
}, {
	"id": 67,
	"Name": "Karen Lewis",
	"Email": "klewis1u@4shared.com",
	"Phone": "1-(251)822-0593",
	"Address": "43 Elka Park",
	"City": "Mobile",
	"Zipcode": "36605",
	"State": "Alabama"
}, {
	"id": 68,
	"Name": "Donna Weaver",
	"Email": "dweaver1v@yolasite.com",
	"Phone": "1-(562)358-7753",
	"Address": "90 Armistice Junction",
	"City": "Los Angeles",
	"Zipcode": "90005",
	"State": "California"
}, {
	"id": 69,
	"Name": "Harold Lawrence",
	"Email": "hlawrence1w@arstechnica.com",
	"Phone": "1-(304)176-2421",
	"Address": "57 Spaight Alley",
	"City": "Charleston",
	"Zipcode": "25326",
	"State": "West Virginia"
}, {
	"id": 70,
	"Name": "Melissa Wheeler",
	"Email": "mwheeler1x@usa.gov",
	"Phone": "1-(775)358-9540",
	"Address": "04 Stuart Circle",
	"City": "Reno",
	"Zipcode": "89550",
	"State": "Nevada"
}, {
	"id": 71,
	"Name": "Lawrence Rose",
	"Email": "lrose1y@ox.ac.uk",
	"Phone": "1-(513)326-8306",
	"Address": "59934 Old Shore Circle",
	"City": "Cincinnati",
	"Zipcode": "45296",
	"State": "Ohio"
}, {
	"id": 72,
	"Name": "Carolyn Stone",
	"Email": "cstone1z@netlog.com",
	"Phone": "1-(803)127-5971",
	"Address": "00437 Grayhawk Park",
	"City": "Columbia",
	"Zipcode": "29225",
	"State": "South Carolina"
}, {
	"id": 73,
	"Name": "Carlos Matthews",
	"Email": "cmatthews20@so-net.ne.jp",
	"Phone": "1-(253)724-5759",
	"Address": "1 Declaration Road",
	"City": "Tacoma",
	"Zipcode": "98481",
	"State": "Washington"
}, {
	"id": 74,
	"Name": "Todd Cooper",
	"Email": "tcooper21@histats.com",
	"Phone": "1-(571)948-3890",
	"Address": "038 Mendota Hill",
	"City": "Falls Church",
	"Zipcode": "22047",
	"State": "Virginia"
}, {
	"id": 75,
	"Name": "Dorothy Gordon",
	"Email": "dgordon22@sourceforge.net",
	"Phone": "1-(714)942-0992",
	"Address": "29 Vahlen Terrace",
	"City": "Santa Ana",
	"Zipcode": "92725",
	"State": "California"
}, {
	"id": 76,
	"Name": "Benjamin Grant",
	"Email": "bgrant23@apple.com",
	"Phone": "1-(512)736-3485",
	"Address": "21 4th Terrace",
	"City": "Austin",
	"Zipcode": "78710",
	"State": "Texas"
}, {
	"id": 77,
	"Name": "Peter Lawson",
	"Email": "plawson24@last.fm",
	"Phone": "1-(814)262-0997",
	"Address": "099 Garrison Court",
	"City": "Erie",
	"Zipcode": "16550",
	"State": "Pennsylvania"
}, {
	"id": 78,
	"Name": "Amanda Bennett",
	"Email": "abennett25@marriott.com",
	"Phone": "1-(260)216-6002",
	"Address": "7590 Atwood Road",
	"City": "Fort Wayne",
	"Zipcode": "46805",
	"State": "Indiana"
}, {
	"id": 79,
	"Name": "Judith Moore",
	"Email": "jmoore26@harvard.edu",
	"Phone": "1-(812)888-5528",
	"Address": "60 Grover Alley",
	"City": "Evansville",
	"Zipcode": "47747",
	"State": "Indiana"
}, {
	"id": 80,
	"Name": "Teresa Robertson",
	"Email": "trobertson27@xrea.com",
	"Phone": "1-(512)687-4361",
	"Address": "282 Eliot Plaza",
	"City": "Austin",
	"Zipcode": "78759",
	"State": "Texas"
}, {
	"id": 81,
	"Name": "Kathy Lee",
	"Email": "klee28@bbc.co.uk",
	"Phone": "1-(614)770-0712",
	"Address": "964 Spohn Terrace",
	"City": "Columbus",
	"Zipcode": "43284",
	"State": "Ohio"
}, {
	"id": 82,
	"Name": "Kathleen Flores",
	"Email": "kflores29@senate.gov",
	"Phone": "1-(208)626-1734",
	"Address": "13 Hintze Drive",
	"City": "Boise",
	"Zipcode": "83757",
	"State": "Idaho"
}, {
	"id": 83,
	"Name": "Susan Long",
	"Email": "slong2a@constantcontact.com",
	"Phone": "1-(202)808-6682",
	"Address": "8 Butterfield Point",
	"City": "Washington",
	"Zipcode": "20046",
	"State": "District of Columbia"
}, {
	"id": 84,
	"Name": "Michelle Alvarez",
	"Email": "malvarez2b@miitbeian.gov.cn",
	"Phone": "1-(713)732-2573",
	"Address": "8837 Nova Terrace",
	"City": "Houston",
	"Zipcode": "77025",
	"State": "Texas"
}, {
	"id": 85,
	"Name": "Shirley Banks",
	"Email": "sbanks2c@vinaora.com",
	"Phone": "1-(813)968-3090",
	"Address": "69102 Menomonie Parkway",
	"City": "Tampa",
	"Zipcode": "33694",
	"State": "Florida"
}, {
	"id": 86,
	"Name": "Diane Lopez",
	"Email": "dlopez2d@amazon.co.jp",
	"Phone": "1-(281)804-1930",
	"Address": "6 Maple Wood Alley",
	"City": "Pasadena",
	"Zipcode": "77505",
	"State": "Texas"
}, {
	"id": 87,
	"Name": "Phyllis Willis",
	"Email": "pwillis2e@blogger.com",
	"Phone": "1-(641)859-2595",
	"Address": "8 Laurel Road",
	"City": "Des Moines",
	"Zipcode": "50315",
	"State": "Iowa"
}, {
	"id": 88,
	"Name": "Ann Martinez",
	"Email": "amartinez2f@umich.edu",
	"Phone": "1-(901)397-4206",
	"Address": "50152 Almo Junction",
	"City": "Memphis",
	"Zipcode": "38188",
	"State": "Tennessee"
}, {
	"id": 89,
	"Name": "Ruth Lane",
	"Email": "rlane2g@state.tx.us",
	"Phone": "1-(320)792-0136",
	"Address": "52 Kenwood Drive",
	"City": "Saint Cloud",
	"Zipcode": "56372",
	"State": "Minnesota"
}, {
	"id": 90,
	"Name": "Christine Fernandez",
	"Email": "cfernandez2h@dot.gov",
	"Phone": "1-(806)456-3760",
	"Address": "06 Sutteridge Street",
	"City": "Lubbock",
	"Zipcode": "79491",
	"State": "Texas"
}, {
	"id": 91,
	"Name": "Benjamin Morrison",
	"Email": "bmorrison2i@devhub.com",
	"Phone": "1-(210)877-5175",
	"Address": "6385 Independence Terrace",
	"City": "San Antonio",
	"Zipcode": "78240",
	"State": "Texas"
}, {
	"id": 92,
	"Name": "Carl Smith",
	"Email": "csmith2j@bloomberg.com",
	"Phone": "1-(504)982-3449",
	"Address": "8 Hovde Junction",
	"City": "New Orleans",
	"Zipcode": "70183",
	"State": "Louisiana"
}, {
	"id": 93,
	"Name": "Amanda Hunter",
	"Email": "ahunter2k@cmu.edu",
	"Phone": "1-(505)444-2228",
	"Address": "9441 Crescent Oaks Street",
	"City": "Las Cruces",
	"Zipcode": "88006",
	"State": "New Mexico"
}, {
	"id": 94,
	"Name": "Sean Cooper",
	"Email": "scooper2l@state.tx.us",
	"Phone": "1-(321)853-1874",
	"Address": "5 Express Terrace",
	"City": "Melbourne",
	"Zipcode": "32919",
	"State": "Florida"
}, {
	"id": 95,
	"Name": "Benjamin Henry",
	"Email": "bhenry2m@amazon.com",
	"Phone": "1-(859)500-8848",
	"Address": "226 Forest Run Drive",
	"City": "Lexington",
	"Zipcode": "40591",
	"State": "Kentucky"
}, {
	"id": 96,
	"Name": "Michael Hart",
	"Email": "mhart2n@google.co.jp",
	"Phone": "1-(402)820-9201",
	"Address": "9831 Arkansas Court",
	"City": "Lincoln",
	"Zipcode": "68524",
	"State": "Nebraska"
}, {
	"id": 97,
	"Name": "Todd Gutierrez",
	"Email": "tgutierrez2o@diigo.com",
	"Phone": "1-(682)332-6290",
	"Address": "0 Green Hill",
	"City": "Fort Worth",
	"Zipcode": "76115",
	"State": "Texas"
}, {
	"id": 98,
	"Name": "Marie Carr",
	"Email": "mcarr2p@squarespace.com",
	"Phone": "1-(757)528-0998",
	"Address": "82 Shopko Plaza",
	"City": "Virginia Beach",
	"Zipcode": "23471",
	"State": "Virginia"
}, {
	"id": 99,
	"Name": "Joe Peterson",
	"Email": "jpeterson2q@comcast.net",
	"Phone": "1-(719)712-9390",
	"Address": "8 Old Gate Place",
	"City": "Pueblo",
	"Zipcode": "81015",
	"State": "Colorado"
}, {
	"id": 100,
	"Name": "Amy Payne",
	"Email": "apayne2r@imgur.com",
	"Phone": "1-(850)463-8363",
	"Address": "2366 Annamark Place",
	"City": "Pensacola",
	"Zipcode": "32575",
	"State": "Florida"
}]